pycoinmarketcap/__init__.py
pycoinmarketcap/coinmarketcap.py
pycoinmarketcap/errors.py
pycoinmarketcap/response.py
pycoinmarketcap/data/__init__.py
pycoinmarketcap/data/cryptocurrency.py
pycoinmarketcap-0.1.0.dist-info/LICENSE
pycoinmarketcap-0.1.0.dist-info/METADATA
pycoinmarketcap-0.1.0.dist-info/WHEEL
pycoinmarketcap-0.1.0.dist-info/top_level.txt
pycoinmarketcap-0.1.0.dist-info/RECORD
