Metadata-Version: 2.1
Name: pycoinmarketcap
Version: 0.1.0
Summary: A simple api wrapper for the CoinMarketCap API
Home-page: https://github.com/World-of-Cryptopups/pycoinmarketcap
Author: TheBoringDude
Author-email: iamcoderx@gmail.com
License: ISC
Project-URL: Bug Tracker, https://github.com/World-of-Cryptopups/pycoinmarketcap/issues
Platform: UNKNOWN
Classifier: License :: OSI Approved :: MIT License
Classifier: Programming Language :: Python :: 3
Classifier: Programming Language :: Python :: 3.7
Classifier: Programming Language :: Python :: 3.8
Classifier: Programming Language :: Python :: 3.9
License-File: LICENSE
Requires-Dist: requests
